ivcap_service/__init__.py
ivcap_service/context.py
ivcap_service/events.py
ivcap_service/ivcap.py
ivcap_service/logger.py
ivcap_service/logging.json
ivcap_service/py.typed
ivcap_service/secret.py
ivcap_service/service.py
ivcap_service/service_definition.py
ivcap_service/testing.py
ivcap_service/tool_definition.py
ivcap_service/types.py
ivcap_service/utils.py
ivcap_service/version.py
ivcap_service-0.6.16.dist-info/AUTHORS.md
ivcap_service-0.6.16.dist-info/LICENSE
ivcap_service-0.6.16.dist-info/METADATA
ivcap_service-0.6.16.dist-info/WHEEL
ivcap_service-0.6.16.dist-info/RECORD
