Metadata-Version: 2.3
Name: ivcap_service
Version: 0.6.16
Summary: SDK library for building services for the IVCAP platform
Author: Max Ott
Author-email: max.ott@csiro.au
Requires-Python: >=3.10,<4.0
Classifier: Programming Language :: Python :: 3
Classifier: Programming Language :: Python :: 3.10
Classifier: Programming Language :: Python :: 3.11
Classifier: Programming Language :: Python :: 3.12
Classifier: Programming Language :: Python :: 3.13
Requires-Dist: cachetools (>=5.5.2,<6.0.0)
Requires-Dist: httpx (>=0.28.1,<0.29.0)
Requires-Dist: ivcap-client (<0.50.0)
Requires-Dist: opentelemetry-distro (>=0.51b0,<0.52)
Requires-Dist: opentelemetry-exporter-otlp (>=1.30.0,<2.0.0)
Requires-Dist: opentelemetry-instrumentation-httpx (>=0.51b0,<0.52)
Requires-Dist: opentelemetry-instrumentation-requests (>=0.51b0,<0.52)
Requires-Dist: pydantic (>=2.11.4,<3.0.0)
